ib1/provenance/__init__.py
ib1/provenance/certificates.py
ib1/provenance/identifier.py
ib1/provenance/record.py
ib1/provenance/signing.py
ib1_provenance-0.5.3.dist-info/LICENSE
ib1_provenance-0.5.3.dist-info/METADATA
ib1_provenance-0.5.3.dist-info/WHEEL
ib1_provenance-0.5.3.dist-info/RECORD
